bytecore/__init__.py
bytecore/accumulator.py
bytecore/bit.py
bytecore/byte.py
bytecore/byte_register.py
bytecore/constant_register.py
bytecore/control_unit.py
bytecore/control_unit_state.py
bytecore/cpu.py
bytecore/emulator.py
bytecore/memory.py
bytecore/memory_bytes_builder.py
bytecore/opcode.py
bytecore/proxy_register.py
bytecore/py.typed
bytecore/register.py
bytecore/replay_register.py
bytecore/state.py
bytecore-1.1.2.dist-info/LICENSE
bytecore-1.1.2.dist-info/METADATA
bytecore-1.1.2.dist-info/WHEEL
bytecore-1.1.2.dist-info/top_level.txt
bytecore-1.1.2.dist-info/RECORD
