Metadata-Version: 2.1
Name: bytecore
Version: 1.1.2
Summary: A minimal, 8-bit CPU emulator designed to help developers explore low-level computing concepts.
Author-email: Joakim Winum Lien <joakim@winum.xyz>
Project-URL: Homepage, https://github.com/joakimwinum/bytecore
Project-URL: Bug Tracker, https://github.com/joakimwinum/bytecore/issues
Classifier: Programming Language :: Python :: 3
Classifier: License :: OSI Approved :: MIT License
Classifier: Operating System :: OS Independent
Requires-Python: >=3.11
License-File: LICENSE
